README.md
setup.py
CHProxy.egg-info/PKG-INFO
CHProxy.egg-info/SOURCES.txt
CHProxy.egg-info/dependency_links.txt
CHProxy.egg-info/top_level.txt
core/__init__.py
core/config.py
core/proxy_helper.py
core/proxy_info.py