Metadata-Version: 2.1
Name: CHProxy
Version: 1.0
Summary: Get long-term proxy from caihongdaili.com
Author: 369
Author-email: luck.yangbo@gmail.com
Classifier: Programming Language :: Python :: 3
Classifier: License :: OSI Approved :: MIT License
Classifier: Operating System :: OS Independent
Requires-Python: >=3.6
